{"feed": "rto", "count": 76, "featured": {"enabled": true, "mode": "deals", "count": 3, "max_payment": null, "manual_rtos": []}, "vehicles": [{"item_id": 3293030377, "rto": "9046", "title": "2014 CADILLAC XTS", "year": "2014", "make": "CADILLAC", "model": "XTS", "color": "WHITE", "type": null, "payment": "279", "mileage": "105362", "status": "On Rent", "sold": true, "has_photo": true, "blurb": "", "image": "images/cars/9046.jpg"}, {"item_id": 3296093215, "rto": "9044", "title": "2012 DODGE Charger", "year": "2012", "make": "DODGE", "model": "Charger", "color": "WHITE", "type": "4DR", "payment": "249", "mileage": "146943", "status": "On Rent", "sold": true, "has_photo": true, "blurb": "", "image": "images/cars/9044.jpg"}, {"item_id": 3276021940, "rto": "9043", "title": "2014 CHEVROLET CRUZE", "year": "2014", "make": "CHEVROLET", "model": "CRUZE", "color": "BLUE", "type": "4DR", "payment": "249", "mileage": "153131", "status": "On Rent", "sold": true, "has_photo": true, "blurb": "", "image": "images/cars/9043.jpg"}, {"item_id": 3270043789, "rto": "9042", "title": "2015 MAZDA CX-5", "year": "2015", "make": "MAZDA", "model": "CX-5", "color": "BLUE", "type": "SUV", "payment": "259", "mileage": "125687", "status": "On Rent", "sold": true, "has_photo": true, "blurb": "", "image": "images/cars/9042.jpg"}, {"item_id": 3264820547, "rto": "9036", "title": "2016 KIA SORENTO", "year": "2016", "make": "KIA", "model": "SORENTO", "color": "GRAY", "type": "SUV", "payment": null, "mileage": "80950", "status": "On Rent", "sold": true, "has_photo": true, "blurb": "", "image": "images/cars/9036.jpg"}, {"item_id": 3264752026, "rto": "9035", "title": "2017 CHEVROLET TRAVERSE", "year": "2017", "make": "CHEVROLET", "model": "TRAVERSE", "color": "BLACK", "type": "SUV", "payment": "249", "mileage": "149666", "status": "Available", "sold": false, "has_photo": true, "blurb": "Cash Price $5995 30-day warranty Engine & trans if pay full price. As-is if less", "image": "images/cars/9035.jpg"}, {"item_id": 3302310601, "rto": "9032", "title": "2015 CHEVROLET TRAVERSE LT", "year": "2015", "make": "CHEVROLET", "model": "TRAVERSE LT", "color": "GRAY", "type": "SUV", "payment": "239", "mileage": "133953", "status": "On Rent", "sold": true, "has_photo": true, "blurb": "", "image": "images/cars/9032.jpg"}, {"item_id": 3214948280, "rto": "9031", "title": "2015 DODGE charger", "year": "2015", "make": "DODGE", "model": "charger", "color": "GRAY", "type": null, "payment": "269", "mileage": "171828", "status": "On Rent", "sold": true, "has_photo": true, "blurb": "", "image": "images/cars/9031.jpg"}, {"item_id": 3097323099, "rto": "9029", "title": "2014 CHEVROLET EQUINOX", "year": "2014", "make": "CHEVROLET", "model": "EQUINOX", "color": "GRAY", "type": "SUV", "payment": "239", "mileage": "126603", "status": "Available", "sold": false, "has_photo": true, "blurb": "Cash Price $6995 30-day warranty Engine & trans if pay full price. As-is if less", "image": "images/cars/9029.jpg"}, {"item_id": 3092008328, "rto": "9028", "title": "2017 HYUNDAI Tucson", "year": "2017", "make": "HYUNDAI", "model": "Tucson", "color": "BLACK", "type": "SUV", "payment": "269", "mileage": "114314", "status": "On Rent", "sold": true, "has_photo": true, "blurb": "Cash Price $8995 30-day warranty Engine & trans if pay full price. As-is if less", "image": "images/cars/9028.jpg"}, {"item_id": 3079988814, "rto": "9027", "title": "2016 CHEVROLET TRAVERSE", "year": "2016", "make": "CHEVROLET", "model": "TRAVERSE", "color": "GOLD", "type": "SUV", "payment": null, "mileage": "147762", "status": "On Rent", "sold": true, "has_photo": false, "blurb": "", "image": "images/cars/no-photo.svg"}, {"item_id": 3075432665, "rto": "9026", "title": "2016 CADILLAC SRX", "year": "2016", "make": "CADILLAC", "model": "SRX", "color": "BLACK", "type": "SUV", "payment": null, "mileage": "140334", "status": "On Rent", "sold": true, "has_photo": false, "blurb": "", "image": "images/cars/no-photo.svg"}, {"item_id": 3065339131, "rto": "9025", "title": "2014 MAZDA CX-5", "year": "2014", "make": "MAZDA", "model": "CX-5", "color": "GRAY", "type": "SUV", "payment": "239", "mileage": "172536", "status": "On Rent", "sold": true, "has_photo": false, "blurb": "", "image": "images/cars/no-photo.svg"}, {"item_id": 3010204820, "rto": "9022", "title": "2015 CHEVROLET CAPTIVA LTZ", "year": "2015", "make": "CHEVROLET", "model": "CAPTIVA LTZ", "color": "WHITE", "type": "SUV", "payment": "239", "mileage": "164003", "status": "Available", "sold": false, "has_photo": true, "blurb": "Cash Price $3995 30-day warranty Engine & trans if pay full price. As-is if less", "image": "images/cars/9022.jpg"}, {"item_id": 3124527510, "rto": "9018", "title": "2015 BMW 320i", "year": "2015", "make": "BMW", "model": "320i", "color": "GRAY", "type": "4DR", "payment": "269", "mileage": "140813", "status": "Available", "sold": false, "has_photo": true, "blurb": "Cash Price $6995 30-day warranty Engine & trans if pay full price. As-is if less", "image": "images/cars/9018.jpg"}, {"item_id": 3049197530, "rto": "9017", "title": "2015 LINCOLN MKC", "year": "2015", "make": "LINCOLN", "model": "MKC", "color": "WHITE", "type": "SUV", "payment": "249", "mileage": "177592", "status": "On Rent", "sold": true, "has_photo": true, "blurb": "", "image": "images/cars/9017.jpg"}, {"item_id": 3124552316, "rto": "9016", "title": "2014 FORD F150 LTD", "year": "2014", "make": "FORD", "model": "F150 LTD", "color": "WHITE", "type": "PKU", "payment": "269", "mileage": "203000", "status": "Available", "sold": false, "has_photo": true, "blurb": "Cash Price $8995 30-day warranty Engine & trans if pay full price. As-is if less", "image": "images/cars/9016.jpg"}, {"item_id": 3124516240, "rto": "9015", "title": "2015 HONDA Odyssey", "year": "2015", "make": "HONDA", "model": "Odyssey", "color": "BLACK", "type": "MINIVAN", "payment": null, "mileage": "151533", "status": "On Rent", "sold": true, "has_photo": true, "blurb": "", "image": "images/cars/9015.jpg"}, {"item_id": 3047522397, "rto": "9013", "title": "2016 KIA Soul", "year": "2016", "make": "KIA", "model": "Soul", "color": "WHITE", "type": "SUV", "payment": "369", "mileage": "187541", "status": "On Rent", "sold": true, "has_photo": true, "blurb": "", "image": "images/cars/9013.jpg"}, {"item_id": 3075128604, "rto": "9012", "title": "2017 FORD ESCAPE", "year": "2017", "make": "FORD", "model": "ESCAPE", "color": "GRAY", "type": "SUV", "payment": "269", "mileage": "151597", "status": "Available", "sold": false, "has_photo": true, "blurb": "Cash Price $6995 30-day warranty Engine & trans if pay full price. As-is if less", "image": "images/cars/9012.jpg"}, {"item_id": 3001141131, "rto": "9011", "title": "2012 JEEP GND CHEROKEE", "year": "2012", "make": "JEEP", "model": "GND CHEROKEE", "color": "WHITE", "type": "SUV", "payment": "239", "mileage": "173983", "status": "On Rent", "sold": true, "has_photo": true, "blurb": "RTOAC TAG", "image": "images/cars/9011.jpg"}, {"item_id": 3042929647, "rto": "9010", "title": "2018 CHEVROLET CRUZE", "year": "2018", "make": "CHEVROLET", "model": "CRUZE", "color": "GRAY", "type": "4DR", "payment": "239", "mileage": "127157", "status": "On Rent", "sold": true, "has_photo": true, "blurb": "", "image": "images/cars/9010.jpg"}, {"item_id": 3040282966, "rto": "9008", "title": "2015 FORD EXPLORER", "year": "2015", "make": "FORD", "model": "EXPLORER", "color": "BLACK", "type": "SUV", "payment": null, "mileage": "167240", "status": "On Rent", "sold": true, "has_photo": true, "blurb": "", "image": "images/cars/9008.jpg"}, {"item_id": 3266642400, "rto": "9007", "title": "2015 NISSAN Rogue", "year": "2015", "make": "NISSAN", "model": "Rogue", "color": "BLACK", "type": "SUV", "payment": "249", "mileage": "128078", "status": "On Rent", "sold": true, "has_photo": true, "blurb": "", "image": "images/cars/9007.jpg"}, {"item_id": 3035196006, "rto": "9006", "title": "2019 DODGE JOURNEY SE", "year": "2019", "make": "DODGE", "model": "JOURNEY SE", "color": "BLACK", "type": "SUV", "payment": "249", "mileage": "124372", "status": "On Rent", "sold": true, "has_photo": true, "blurb": "", "image": "images/cars/9006.jpg"}, {"item_id": 3034341852, "rto": "9004", "title": "2018 FORD EDGE SEL", "year": "2018", "make": "FORD", "model": "EDGE SEL", "color": "GOLD", "type": "SUV", "payment": null, "mileage": "146920", "status": "On Rent", "sold": true, "has_photo": true, "blurb": "RTOAC TAG", "image": "images/cars/9004.jpg"}, {"item_id": 3027615631, "rto": "9003", "title": "2018 KIA SPORTAGE", "year": "2018", "make": "KIA", "model": "SPORTAGE", "color": "BLUE", "type": null, "payment": "239", "mileage": "145443", "status": "On Rent", "sold": true, "has_photo": true, "blurb": "", "image": "images/cars/9003.jpg"}, {"item_id": 2963458784, "rto": "9002", "title": "2016 KIA OPTIMA", "year": "2016", "make": "KIA", "model": "OPTIMA", "color": "WHITE", "type": "4DR", "payment": "259", "mileage": "72210", "status": "On Rent", "sold": true, "has_photo": true, "blurb": "", "image": "images/cars/9002.jpg"}, {"item_id": 2950381427, "rto": "9001", "title": "2012 BUICK VERANO", "year": "2012", "make": "BUICK", "model": "VERANO", "color": "BEIGE", "type": "2DR", "payment": "239", "mileage": "168401", "status": "Available", "sold": false, "has_photo": true, "blurb": "Cash Price $2995 30-day warranty Engine & trans if pay full price. As-is if less", "image": "images/cars/9001.jpg"}, {"item_id": 2757497846, "rto": "8255", "title": "2013 TOYOTA COROLLA", "year": "2013", "make": "TOYOTA", "model": "COROLLA", "color": "BLACK", "type": "4DR", "payment": "329", "mileage": "122116", "status": "On Rent", "sold": true, "has_photo": true, "blurb": "Cash Price $5995 30-day warranty Engine & trans if pay full price. As-is if less", "image": "images/cars/8255.jpg"}, {"item_id": 2757497557, "rto": "8250", "title": "2006 CHRYSLER PT CRUISER", "year": "2006", "make": "CHRYSLER", "model": "PT CRUISER", "color": "WHITE", "type": "4DR", "payment": "210", "mileage": "89684", "status": "Available", "sold": false, "has_photo": true, "blurb": "Cash Price $2995 30-day warranty Engine & trans if pay full price. As-is if less", "image": "images/cars/8250.jpg"}, {"item_id": 2757497668, "rto": "8245", "title": "2006 FORD FUSION", "year": "2006", "make": "FORD", "model": "FUSION", "color": "GREEN", "type": "4DR", "payment": "239", "mileage": "143481", "status": "Available", "sold": false, "has_photo": true, "blurb": "Cash Price $1995 30-day warranty Engine & trans if pay full price. As-is if less", "image": "images/cars/8245.jpg"}, {"item_id": 2757497859, "rto": "8243", "title": "2013 FORD FOCUS", "year": "2013", "make": "FORD", "model": "FOCUS", "color": "BLUE", "type": "4DR", "payment": "239", "mileage": "132420", "status": "Available", "sold": false, "has_photo": true, "blurb": "Cash Price $4995 30-day warranty Engine & trans if pay full price. As-is if less", "image": "images/cars/8243.jpg"}, {"item_id": 2757497702, "rto": "8241", "title": "2016 CHEVROLET IMPALA LTD", "year": "2016", "make": "CHEVROLET", "model": "IMPALA LTD", "color": "GRAY", "type": "4DR", "payment": "250", "mileage": "114328", "status": "On Rent", "sold": true, "has_photo": true, "blurb": "RTOAC TAG", "image": "images/cars/8241.jpg"}, {"item_id": 2757497661, "rto": "8236", "title": "2016 KIA SOUL", "year": "2016", "make": "KIA", "model": "SOUL", "color": "GRAY", "type": "4DR", "payment": "250", "mileage": "129172", "status": "Available", "sold": false, "has_photo": true, "blurb": "Cash Price $4995 30-day warranty Engine & trans if pay full price. As-is if less", "image": "images/cars/8236.jpg"}, {"item_id": 2757497866, "rto": "8230", "title": "2011 TOYOTA COROLLA", "year": "2011", "make": "TOYOTA", "model": "COROLLA", "color": "RED", "type": "4DR", "payment": "249", "mileage": "176905", "status": "Available", "sold": false, "has_photo": true, "blurb": "Cash Price $3995 30-day warranty Engine & trans if pay full price. As-is if less", "image": "images/cars/8230.jpg"}, {"item_id": 2757497514, "rto": "8223", "title": "2014 FORD ESCAPE SE", "year": "2014", "make": "FORD", "model": "ESCAPE SE", "color": "ORANGE", "type": "SUV", "payment": "249", "mileage": "125171", "status": "Available", "sold": false, "has_photo": true, "blurb": "Cash Price $4995 30-day warranty Engine & trans if pay full price. As-is if less", "image": "images/cars/8223.jpg"}, {"item_id": 2781276340, "rto": "8217", "title": "2012 VOLKSWAGEN PASSAT S", "year": "2012", "make": "VOLKSWAGEN", "model": "PASSAT S", "color": "WHITE", "type": "4DR", "payment": "249", "mileage": "140820", "status": "On Rent", "sold": true, "has_photo": true, "blurb": "Cash Price $3995 30-day warranty Engine & trans if pay full price. As-is if less", "image": "images/cars/8217.jpg"}, {"item_id": 2757497481, "rto": "8200", "title": "2013 JEEP PATRIOT", "year": "2013", "make": "JEEP", "model": "PATRIOT", "color": "RED", "type": "SUV", "payment": "260", "mileage": "166168", "status": "Available", "sold": false, "has_photo": true, "blurb": "Cash Price $2995 30-day warranty Engine & trans if pay full price. As-is if less", "image": "images/cars/8200.jpg"}, {"item_id": 2757497829, "rto": "8193", "title": "2016 HYUNDAI ELANTRA", "year": "2016", "make": "HYUNDAI", "model": "ELANTRA", "color": "WHITE", "type": "4DR", "payment": "250", "mileage": "150146", "status": "Available", "sold": false, "has_photo": true, "blurb": "Cash Price $3495 30-day warranty Engine & trans if pay full price. As-is if less", "image": "images/cars/8193.jpg"}, {"item_id": 2757497826, "rto": "8178", "title": "2016 HYUNDAI ACCENT SE", "year": "2016", "make": "HYUNDAI", "model": "ACCENT SE", "color": "BEIGE", "type": "4DR", "payment": "240", "mileage": "141621", "status": "On Rent", "sold": true, "has_photo": true, "blurb": "", "image": "images/cars/8178.jpg"}, {"item_id": 2781276255, "rto": "8149", "title": "2014 BUICK VERANO", "year": "2014", "make": "BUICK", "model": "VERANO", "color": "RED", "type": "4DR", "payment": "220", "mileage": "199364", "status": "On Rent", "sold": true, "has_photo": true, "blurb": "Cash Price $3495 30-day warranty Engine & trans if pay full price. As-is if less", "image": "images/cars/8149.jpg"}, {"item_id": 2757497850, "rto": "8148", "title": "2013 CHRYSLER TOWN & COUNTRY", "year": "2013", "make": "CHRYSLER", "model": "TOWN & COUNTRY", "color": "SILVER", "type": "VAN", "payment": "250", "mileage": "189890", "status": "On Rent", "sold": true, "has_photo": true, "blurb": "RTOAC", "image": "images/cars/8148.jpg"}, {"item_id": 2781276234, "rto": "8147", "title": "2016 DODGE JOURNEY SXT", "year": "2016", "make": "DODGE", "model": "JOURNEY SXT", "color": "BLACK", "type": "SUV", "payment": "270", "mileage": "180619", "status": "On Rent", "sold": true, "has_photo": true, "blurb": "RTOAC TAG", "image": "images/cars/8147.jpg"}, {"item_id": 2757497649, "rto": "8145", "title": "2014 CHEVROLET SONIC", "year": "2014", "make": "CHEVROLET", "model": "SONIC", "color": "WHITE", "type": "4DR", "payment": "239", "mileage": "119964", "status": "Available", "sold": false, "has_photo": true, "blurb": "Cash Price $3995 30-day warranty Engine & trans if pay full price. As-is if less", "image": "images/cars/8145.jpg"}, {"item_id": 2757497366, "rto": "8141", "title": "2009 DODGE CHALLENGER", "year": "2009", "make": "DODGE", "model": "CHALLENGER", "color": "RED", "type": "2DR", "payment": "280", "mileage": "168246", "status": "On Rent", "sold": true, "has_photo": true, "blurb": "", "image": "images/cars/8141.jpg"}, {"item_id": 2757497810, "rto": "8132", "title": "2013 HYUNDAI SONATA", "year": "2013", "make": "HYUNDAI", "model": "SONATA", "color": "RED", "type": "4DR", "payment": "240", "mileage": "169877", "status": "On Rent", "sold": true, "has_photo": true, "blurb": "Cash Price $3995 30-day warranty Engine & trans if pay full price. As-is if less", "image": "images/cars/8132.jpg"}, {"item_id": 2757497510, "rto": "8092", "title": "2013 DODGE CHARGER SE", "year": "2013", "make": "DODGE", "model": "CHARGER SE", "color": "BLACK", "type": "4DR", "payment": "279", "mileage": "154177", "status": "On Rent", "sold": true, "has_photo": true, "blurb": "", "image": "images/cars/8092.jpg"}, {"item_id": 2757497874, "rto": "8036", "title": "2012 TOYOTA CAMRY", "year": "2012", "make": "TOYOTA", "model": "CAMRY", "color": "GRAY", "type": "4DR", "payment": "249", "mileage": "239889", "status": "Available", "sold": false, "has_photo": true, "blurb": "Cash Price $4995 30-day warranty Engine & trans if pay full price. As-is if less", "image": "images/cars/8036.jpg"}, {"item_id": 2757497772, "rto": "8030", "title": "2015 FORD FOCUS SE", "year": "2015", "make": "FORD", "model": "FOCUS SE", "color": "RED", "type": null, "payment": "240", "mileage": "124095", "status": "Available", "sold": false, "has_photo": true, "blurb": "Cash Price $4995 30-day warranty Engine & trans if pay full price. As-is if less", "image": "images/cars/8030.jpg"}, {"item_id": 2757497870, "rto": "8009", "title": "2012 TOYOTA SIENNA LE", "year": "2012", "make": "TOYOTA", "model": "SIENNA LE", "color": "GOLD", "type": "VAN", "payment": "250", "mileage": "137331", "status": "On Rent", "sold": true, "has_photo": true, "blurb": "", "image": "images/cars/8009.jpg"}, {"item_id": 2757497352, "rto": "7310", "title": "2008 CADILLAC DTS", "year": "2008", "make": "CADILLAC", "model": "DTS", "color": "RED", "type": "4DR", "payment": "250", "mileage": "102273", "status": "On Rent", "sold": true, "has_photo": true, "blurb": "Cash Price $2995 30-day warranty Engine & trans if pay full price. As-is if less", "image": "images/cars/7310.jpg"}, {"item_id": 2757497343, "rto": "7309", "title": "2012 CHEVROLET CRUZE", "year": "2012", "make": "CHEVROLET", "model": "CRUZE", "color": "BLACK", "type": "4DR", "payment": "249", "mileage": "133556", "status": "On Rent", "sold": true, "has_photo": true, "blurb": "Cash Price $3995 30-day warranty Engine & trans if pay full price. As-is if less", "image": "images/cars/7309.jpg"}, {"item_id": 2757497338, "rto": "7308", "title": "2014 CHEVROLET IMPALA LIMITED", "year": "2014", "make": "CHEVROLET", "model": "IMPALA LIMITED", "color": "RED", "type": null, "payment": "240", "mileage": "158900", "status": "On Rent", "sold": true, "has_photo": true, "blurb": "", "image": "images/cars/7308.jpg"}, {"item_id": 2757497319, "rto": "7303", "title": "2013 HYUNDAI SONATA", "year": "2013", "make": "HYUNDAI", "model": "SONATA", "color": "GRAY", "type": "4DR", "payment": "240", "mileage": "142243", "status": "On Rent", "sold": true, "has_photo": true, "blurb": "RTOAC TAG", "image": "images/cars/7303.jpg"}, {"item_id": 2757497317, "rto": "7302", "title": "2013 HYUNDAI ELANTRA", "year": "2013", "make": "HYUNDAI", "model": "ELANTRA", "color": "RED", "type": "4DR", "payment": "240", "mileage": "141274", "status": "On Rent", "sold": true, "has_photo": true, "blurb": "RTOAC TAG", "image": "images/cars/7302.jpg"}, {"item_id": 2757497313, "rto": "7301", "title": "2012 HYUNDAI GENESIS", "year": "2012", "make": "HYUNDAI", "model": "GENESIS", "color": "GOLD", "type": "4DR", "payment": "240", "mileage": "110628", "status": "On Rent", "sold": true, "has_photo": true, "blurb": "Cash Price $3995 30-day warranty Engine & trans if pay full price. As-is if less", "image": "images/cars/7301.jpg"}, {"item_id": 2757497294, "rto": "7298", "title": "2017 KIA FORTE", "year": "2017", "make": "KIA", "model": "FORTE", "color": "WHITE", "type": "4DR", "payment": "250", "mileage": "146485", "status": "On Rent", "sold": true, "has_photo": true, "blurb": "1/2 off sale @ CITY KIA", "image": "images/cars/7298.jpg"}, {"item_id": 2757497279, "rto": "7295", "title": "2009 TOYOTA AVALON", "year": "2009", "make": "TOYOTA", "model": "AVALON", "color": "WHITE", "type": "4DR", "payment": "240", "mileage": "117153", "status": "Available", "sold": false, "has_photo": true, "blurb": "Cash Price $5995 30-day warranty Engine & trans if pay full price. As-is if less", "image": "images/cars/7295.jpg"}, {"item_id": 2757497270, "rto": "7292", "title": "2009 BMW 5 SERIES cash", "year": "2009", "make": "BMW", "model": "5 SERIES cash", "color": "BLUE", "type": "4DR", "payment": "249", "mileage": "110220", "status": "Available", "sold": false, "has_photo": true, "blurb": "Cash Price $4995 30-day warranty Engine & trans if pay full price. As-is if less", "image": "images/cars/7292.jpg"}, {"item_id": 2757497240, "rto": "7287", "title": "2012 FORD FUSION", "year": "2012", "make": "FORD", "model": "FUSION", "color": "WHITE", "type": "4DR", "payment": "250", "mileage": "109367", "status": "Available", "sold": false, "has_photo": true, "blurb": "Cash Price $4995 30-day warranty Engine & trans if pay full price. As-is if less", "image": "images/cars/7287.jpg"}, {"item_id": 2757497234, "rto": "7286", "title": "2011 CHEVROLET HHR", "year": "2011", "make": "CHEVROLET", "model": "HHR", "color": "GRAY", "type": "4DR", "payment": "239", "mileage": "139831", "status": "Available", "sold": false, "has_photo": true, "blurb": "Cash Price $2995 30-day warranty Engine & trans if pay full price. As-is if less", "image": "images/cars/7286.jpg"}, {"item_id": 2757497212, "rto": "7280", "title": "2016 JEEP RENEGADE", "year": "2016", "make": "JEEP", "model": "RENEGADE", "color": "GRAY", "type": "SUV", "payment": "250", "mileage": "147059", "status": "On Rent", "sold": true, "has_photo": true, "blurb": "", "image": "images/cars/7280.jpg"}, {"item_id": 2757497208, "rto": "7279", "title": "2011 TOYOTA CAMRY", "year": "2011", "make": "TOYOTA", "model": "CAMRY", "color": "GRAY", "type": "4DR", "payment": "249", "mileage": "129665", "status": "On Rent", "sold": true, "has_photo": true, "blurb": "", "image": "images/cars/7279.jpg"}, {"item_id": 2757497203, "rto": "7278", "title": "2013 CADILLAC ATS", "year": "2013", "make": "CADILLAC", "model": "ATS", "color": "WHITE", "type": "4DR", "payment": "270", "mileage": "166674", "status": "On Rent", "sold": true, "has_photo": true, "blurb": "1/2 off sale", "image": "images/cars/7278.jpg"}, {"item_id": 2757497200, "rto": "7277", "title": "2016 BUICK ENCORE", "year": "2016", "make": "BUICK", "model": "ENCORE", "color": "BLACK", "type": "SUV", "payment": "245", "mileage": "145259", "status": "On Rent", "sold": true, "has_photo": true, "blurb": "", "image": "images/cars/7277.jpg"}, {"item_id": 2757497187, "rto": "7274", "title": "2012 CHEVROLET TRAVERSE", "year": "2012", "make": "CHEVROLET", "model": "TRAVERSE", "color": "BLACK", "type": "SUV", "payment": "250", "mileage": "187467", "status": "On Rent", "sold": true, "has_photo": true, "blurb": "1/2 OFF AT $1,000  Getting radio installed", "image": "images/cars/7274.jpg"}, {"item_id": 2757497171, "rto": "7271", "title": "2008 LEXUS IS 250", "year": "2008", "make": "LEXUS", "model": "IS 250", "color": "WHITE", "type": "4DR", "payment": "250", "mileage": "124577", "status": "On Rent", "sold": true, "has_photo": true, "blurb": "", "image": "images/cars/7271.jpg"}, {"item_id": 2757497161, "rto": "7269", "title": "2014 DODGE GRAND CARAVAN", "year": "2014", "make": "DODGE", "model": "GRAND CARAVAN", "color": "RED", "type": "VAN", "payment": "259", "mileage": "135146", "status": "On Rent", "sold": true, "has_photo": true, "blurb": "", "image": "images/cars/7269.jpg"}, {"item_id": 2757496990, "rto": "7261", "title": "2009 GMC YUKON", "year": "2009", "make": "GMC", "model": "YUKON", "color": "BLUE", "type": "SUV", "payment": "249", "mileage": "214030", "status": "On Rent", "sold": true, "has_photo": true, "blurb": "", "image": "images/cars/7261.jpg"}, {"item_id": 2757496935, "rto": "7249", "title": "2015 FORD TAURUS", "year": "2015", "make": "FORD", "model": "TAURUS", "color": "SILVER", "type": "4DR", "payment": "229", "mileage": "200516", "status": "On Rent", "sold": true, "has_photo": false, "blurb": "$500 DOWN", "image": "images/cars/no-photo.svg"}, {"item_id": 2757496873, "rto": "7237", "title": "2016 FORD FOCUS", "year": "2016", "make": "FORD", "model": "FOCUS", "color": "RED", "type": "4DR", "payment": "250", "mileage": "172447", "status": "On Rent", "sold": true, "has_photo": true, "blurb": "1/2 off sale", "image": "images/cars/7237.jpg"}, {"item_id": 2757496858, "rto": "7234", "title": "2014 BUICK ENCORE", "year": "2014", "make": "BUICK", "model": "ENCORE", "color": "WHITE", "type": "SUV", "payment": "249", "mileage": "190070", "status": "Available", "sold": false, "has_photo": true, "blurb": "Cash Price $1995 30-day warranty Engine & trans if pay full price. As-is if less", "image": "images/cars/7234.jpg"}, {"item_id": 2757496734, "rto": "7210", "title": "2015 CHRYSLER 200 Limited 2.4 DOHC", "year": "2015", "make": "CHRYSLER", "model": "200 Limited 2.4 DOHC", "color": "SILVER", "type": "4DR", "payment": "249", "mileage": "139427", "status": "On Rent", "sold": true, "has_photo": true, "blurb": "Cash Price $4995 30-day warranty Engine & trans if pay full price. As-is if less", "image": "images/cars/7210.jpg"}, {"item_id": 2757496525, "rto": "7172", "title": "2016 FORD FUSION", "year": "2016", "make": "FORD", "model": "FUSION", "color": "SILVER", "type": "4DR", "payment": "250", "mileage": "128225", "status": "On Rent", "sold": true, "has_photo": true, "blurb": "", "image": "images/cars/7172.jpg"}, {"item_id": 2757496205, "rto": "7092", "title": "2004 DODGE RAM 1500 4X2", "year": "2004", "make": "DODGE", "model": "RAM 1500 4X2", "color": "SILVER", "type": "PKU", "payment": "249", "mileage": "117491", "status": "Available", "sold": false, "has_photo": true, "blurb": "Cash Price $4995 30-day warranty Engine & trans if pay full price. As-is if less", "image": "images/cars/7092.jpg"}], "show_mileage": false, "phone": "321-319-4300"}